setup.cfg
setup.py
django_gen_settings/GenSettingDict.py
django_gen_settings/__init__.py
django_gen_settings/fields.py
django_gen_settings/models.py
django_gen_settings/tests.py
django_gen_settings/views.py
django_gen_settings.egg-info/PKG-INFO
django_gen_settings.egg-info/SOURCES.txt
django_gen_settings.egg-info/dependency_links.txt
django_gen_settings.egg-info/requires.txt
django_gen_settings.egg-info/top_level.txt
django_gen_settings/templatetags/__init__.py
django_gen_settings/templatetags/gen_settings.py