Metadata-Version: 1.1
Name: django-gen-settings
Version: 0.2
Summary: A settings mixin for django models
Home-page: https://github.com/paulgueltekin/django-gen-settings
Author: Paul Gueltekin
Author-email: paul@gueltekin.at
License: UNKNOWN
Download-URL: https://github.com/paulgueltekin/django-gen-settings/tarball/0.2
Keywords: django,settings,model,mixin
Platform: UNKNOWN
